CHANGELOG.md
README.md
requirements.txt
setup.cfg
setup.py
pgcrypt/__init__.py
pgcrypt/compressor.py
pgcrypt/detector.py
pgcrypt/enums.py
pgcrypt/errors.py
pgcrypt/header.py
pgcrypt/metadata.py
pgcrypt/offset.py
pgcrypt/reader.py
pgcrypt/writer.py
pgcrypt/zstdstream.py
pgcrypt.egg-info/PKG-INFO
pgcrypt.egg-info/SOURCES.txt
pgcrypt.egg-info/dependency_links.txt
pgcrypt.egg-info/not-zip-safe
pgcrypt.egg-info/requires.txt
pgcrypt.egg-info/top_level.txt