Metadata-Version: 2.1
Name: pgcrypt
Version: 0.1.1
Summary: PGCopy dump packed into LZ4, ZSTD or uncompressed with meta data information packed into zlib.
Home-page: https://github.com/0xMihalich/pgcrypt
Author: 0xMihalich
Author-email: bayanmobile87@gmail.com
License-File: README.md
License-File: CHANGELOG.md
Requires-Dist: lz4>=4.4.4
Requires-Dist: zstd>=1.5.7.2
Requires-Dist: zstandard>=0.24.0
Requires-Dist: pandas>=2.1.0
Requires-Dist: polars>=0.20.31
Requires-Dist: pgcopylib==0.1.1
